adabelief/__init__.py
adabelief/adabelief.py
adabelief_slim-0.0.1.dist-info/LICENSE
adabelief_slim-0.0.1.dist-info/METADATA
adabelief_slim-0.0.1.dist-info/WHEEL
adabelief_slim-0.0.1.dist-info/top_level.txt
adabelief_slim-0.0.1.dist-info/RECORD
